app/__init__.py
app/_version.py
app/exceptions.py
app/version.py
app/config/__init__.py
app/config/logging_config.py
app/config/settings.py
app/events/__init__.py
app/events/event_bus.py
app/middleware/auth.py
app/middleware/logging_middleware.py
app/models/__init__.py
app/models/activity_models.py
app/models/code_artifact_models.py
app/models/document_models.py
app/models/entity_models.py
app/models/graph_models.py
app/models/memory_models.py
app/models/models.py
app/models/project_models.py
app/models/tool_registry_models.py
app/models/user_models.py
app/protocols/__init__.py
app/protocols/activity_protocol.py
app/protocols/code_artifact_protocol.py
app/protocols/document_protocol.py
app/protocols/entity_protocol.py
app/protocols/memory_protocol.py
app/protocols/project_protocol.py
app/protocols/user_protocol.py
app/repositories/__init__.py
app/repositories/helpers.py
app/repositories/embeddings/__init__.py
app/repositories/embeddings/embedding_adapter.py
app/repositories/embeddings/reranker_adapter.py
app/repositories/postgres/__init__.py
app/repositories/postgres/activity_repository.py
app/repositories/postgres/code_artifact_repository.py
app/repositories/postgres/document_repository.py
app/repositories/postgres/entity_repository.py
app/repositories/postgres/memory_repository.py
app/repositories/postgres/postgres_adapter.py
app/repositories/postgres/postgres_tables.py
app/repositories/postgres/project_repository.py
app/repositories/postgres/user_repository.py
app/repositories/sqlite/activity_repository.py
app/repositories/sqlite/code_artifact_repository.py
app/repositories/sqlite/document_repository.py
app/repositories/sqlite/entity_repository.py
app/repositories/sqlite/memory_repository.py
app/repositories/sqlite/project_repository.py
app/repositories/sqlite/sqlite_adapter.py
app/repositories/sqlite/sqlite_tables.py
app/repositories/sqlite/user_repository.py
app/routes/__init__.py
app/routes/api/__init__.py
app/routes/api/activity.py
app/routes/api/auth.py
forgetful_ai-0.2.0.dist-info/METADATA
forgetful_ai-0.2.0.dist-info/WHEEL
forgetful_ai-0.2.0.dist-info/entry_points.txt
forgetful_ai-0.2.0.dist-info/licenses/LICENCE.md
forgetful_ai-0.2.0.dist-info/RECORD
