Metadata-Version: 2.4
Name: forgetful-ai
Version: 0.2.0
Summary: MCP Server for AI Agent Memory - persistent, semantically-searchable memory for AI agents
Project-URL: Homepage, https://github.com/scottrbk/forgetful
Project-URL: Repository, https://github.com/scottrbk/forgetful
Project-URL: Issues, https://github.com/scottrbk/forgetful/issues
Author-email: Scott <scott@example.com>
License: MIT
License-File: LICENCE.md
Classifier: Development Status :: 4 - Beta
Classifier: Intended Audience :: Developers
Classifier: License :: OSI Approved :: MIT License
Classifier: Operating System :: OS Independent
Classifier: Programming Language :: Python :: 3.12
Classifier: Topic :: Scientific/Engineering :: Artificial Intelligence
Requires-Python: >=3.12
Requires-Dist: aiosqlite>=0.21.0
Requires-Dist: alembic>=1.17.2
Requires-Dist: asyncpg>=0.30.0
Requires-Dist: dotenv>=0.9.9
Requires-Dist: fastapi>=0.116.1
Requires-Dist: fastembed>=0.7.3
Requires-Dist: fastmcp>=2.14.1
Requires-Dist: google-generativeai>=0.8.5
Requires-Dist: httpx>=0.28.1
Requires-Dist: openai>=2.8.0
Requires-Dist: pgvector>=0.4.1
Requires-Dist: platformdirs>=4.0.0
Requires-Dist: psycopg2-binary>=2.9.11
Requires-Dist: pydantic-settings>=2.10.1
Requires-Dist: pydantic>=2.11.7
Requires-Dist: pytest-asyncio>=0.24.0
Requires-Dist: pytest>=8.4.1
Requires-Dist: requests>=2.32.5
Requires-Dist: sqlalchemy[asyncio]>=2.0.44
Requires-Dist: sqlite-vec>=0.1.6
Requires-Dist: tiktoken>=0.12.0
Requires-Dist: uvicorn>=0.35.0
